{
  "meta": {
    "id": "solarized-dark",
    "name": "Solarized Dark",
    "mode": "dark",
    "description": "Sprint 3 migration: Ethan Schoonover Solarized Dark — base03 ink + ANSI accent rainbow. Source: pinboard-themes.js §solarized-dark."
  },
  "layout": {
    "mode": "classic-list",
    "max-width": "1030px",
    "bookmark-style": "card",
    "right-bar": "visible"
  },
  "palette": {
    "bg": "#002b36",
    "bg-surface": "#073642",
    "fg": "#839496",
    "fg-strong": "#93a1a1",
    "muted": "#586e75",
    "muted-soft": "#586e75",
    "border": "#094b5a",
    "border-strong": "#586e75",
    "border-soft": "#094b5a",
    "accent": "#268bd2",
    "accent-hover": "#2aa198",
    "accent-soft": "#073642",
    "accent-alpha": "rgba(38,139,210,0.25)",
    "input-bg": "#073642",
    "private-bg": "#073642",
    "private-accent": "#b58900",
    "selection-bg": "#0a4a5a",
    "selection-fg": "#eee8d5",
    "tag-bg": "transparent",
    "tag-fg": "#2aa198",
    "row-hover": "#073642",
    "destroy": "#dc322f",
    "btn-bg": "#268bd2",
    "btn-fg": "#fdf6e3",
    "success": "#859900",
    "success-hover": "#2aa198",
    "url-link-bg": "#073642",
    "url-link-fg": "#b58900",
    "link-hover": "#2aa198",
    "link-visited": "#268bd2",
    "focus-ring": "#268bd2",
    "unread": "#dc322f"
  },
  "typo": {
    "family": "\"Inter\", -apple-system, sans-serif",
    "size-base": "13px",
    "size-lg": "15px",
    "size-sm": "12px",
    "size-xs": "11px",
    "line-height": 1.5,
    "weight-body": 400,
    "weight-heading": 700
  },
  "space": {
    "unit": "4px",
    "bookmark-gap": "6px",
    "main-padding": "12px",
    "sub-banner-y": "8px",
    "right-bar-gap": "12px",
    "form-gap": "8px"
  },
  "radius": {
    "sm": "2px",
    "md": "4px",
    "lg": "2px"
  },
  "border": {
    "width": "1px",
    "style": "solid"
  },
  "ext": {
    "private-style": "border-left",
    "private-border-width": "2px"
  },
  "overrides": {
    "css": "/* ======== overrides-patch for solarized-dark (auto-generated by tools/generate-overrides.mjs) ========\n * Restores shipped decls the composer's token-driven output doesn't match.\n */\n\nbody#pinboard { letter-spacing: 0.01em !important; }\n#banner { border-radius: 4px !important; padding: 8px 16px !important; }\n#search_query_field { width: 100% !important; background: #002b36 !important; }\n.bookmark { border-bottom: 1px solid #094b5a !important; padding: 12px 14px !important; border-radius: 2px !important; border-left: 2px solid transparent !important; }\nbody:not(#pinboard) { letter-spacing: 0.01em !important; }\n#sub_banner a { color: #93a1a1 !important; }\n#banner_searchbox input[type=\"text\"] { background: #002b36 !important; }\n#search_query_field:focus { background: #073642 !important; }\n#banner_searchbox input[type=\"text\"]:focus { background: #073642 !important; }\n.search_button input[type=\"submit\"] { text-transform: uppercase !important; font-size: 11px !important; letter-spacing: 0.05em !important; }\n.bookmark:hover { border-left-color: #268bd2 !important; }\na.bookmark_title { font-weight: 500 !important; }\na.url_display { color: #859900 !important; font-family: \"Fira Code\", \"Cascadia Code\", monospace !important; }\na.url_link { background: #002b36 !important; padding: 1px 5px !important; }\n.description { opacity: 0.8 !important; }\n.description blockquote { color: #93a1a1 !important; border-left: 2px solid #268bd2 !important; }\na.tag { font-family: \"Fira Code\", \"Cascadia Code\", monospace !important; letter-spacing: 0.02em !important; }\na.tag:hover { color: #268bd2 !important; text-decoration: underline !important; }\na.when { font-family: \"Fira Code\", \"Cascadia Code\", monospace !important; }\n.edit_links a:hover { color: #93a1a1 !important; }\n#right_bar h3 { color: #93a1a1 !important; }\n#right_bar h4 { color: #93a1a1 !important; }\n#right_bar b { color: #93a1a1 !important; }\na.tag.selected { color: #d33682 !important; }\na.sort_order_selected { background: #073642 !important; }\n.suggested_tag { color: #2aa198 !important; }\n.settings_tab { color: #93a1a1 !important; }\n.settings_heading { color: #93a1a1 !important; text-transform: uppercase !important; font-size: 12px !important; letter-spacing: 0.08em !important; }\n.service_box { border-radius: 2px !important; }\n.help_box { border-radius: 2px !important; }\n#profile_main_column h2 { color: #93a1a1 !important; }\n#profile_left_column h2 { color: #93a1a1 !important; }\n#profile_right_column h2 { color: #93a1a1 !important; }\n.bookmark_count { color: #93a1a1 !important; }\n.bookmark_count_box { color: #93a1a1 !important; }\nh2 { color: #93a1a1 !important; }\n#main_column form[name=\"sort\"] table tr:hover { background: rgba(38,139,210,0.1) !important; }\n#main_column form[name=\"sort\"] table input[name^=\"id_\"] { width: 38px !important; min-width: 38px !important; max-width: 38px !important; padding: 3px 4px !important; margin-right: 10px !important; font-size: 12px !important; line-height: 1.2 !important; border-radius: 3px !important; box-sizing: border-box !important; vertical-align: middle !important; border: 1px solid #586e75 !important; font-weight: 600 !important; }\n#main_column form[name=\"sort\"] table input[name^=\"id_\"]:focus { box-shadow: 0 0 0 2px rgba(38,139,210,0.3) !important; }\n#main_column form[name=\"sort\"] table a.bundle { font-weight: 600 !important; letter-spacing: 0.02em !important; border-radius: 3px !important; }\n#main_column form[name=\"sort\"] table td a.destroy { font-weight: 600 !important; }\n#right_bar table td a.tag { color: #93a1a1 !important; }\n#right_bar input#key { background: #002b36 !important; color: #93a1a1 !important; border: 1px solid #586e75 !important; border-radius: 4px !important; }\n#right_bar input[type=\"submit\"] { background: #268bd2 !important; border-radius: 4px !important; }\n#tweet_searchbox #search_query_field { background: #002b36 !important; color: #93a1a1 !important; border: 1px solid #586e75 !important; border-radius: 4px !important; font-size: 13px !important; }\n#tweet_searchbox input[type=\"submit\"] { background: #268bd2 !important; border-radius: 4px !important; }"
  }
}